git_safe/__init__.py
git_safe/cli.py
git_safe/constants.py
git_safe/crypto.py
git_safe/file_ops.py
git_safe/keyfile.py
git_safe/patterns.py
gitsafe_cli-1.0.1.data/scripts/git-safe
gitsafe_cli-1.0.1.dist-info/licenses/LICENSE
gitsafe_cli-1.0.1.dist-info/METADATA
gitsafe_cli-1.0.1.dist-info/WHEEL
gitsafe_cli-1.0.1.dist-info/entry_points.txt
gitsafe_cli-1.0.1.dist-info/top_level.txt
gitsafe_cli-1.0.1.dist-info/RECORD
