Metadata-Version: 2.4
Name: gitsafe-cli
Version: 1.0.1
Summary: Effortless file encryption for your git repos—pattern-matched, secure, and keyfile-flexible.
Home-page: https://github.com/hemonserrat/git-safe
Author: Hernan Monserrat
Author-email: 
License: MIT
Project-URL: Homepage, https://github.com/hemonserrat/git-safe
Project-URL: Bug Reports, https://github.com/hemonserrat/git-safe/issues
Project-URL: Source, https://github.com/hemonserrat/git-safe
Project-URL: Documentation, https://github.com/hemonserrat/git-safe#readme
Keywords: git,encryption,security,cryptography,file-encryption,gitattributes
Classifier: Development Status :: 4 - Beta
Classifier: Intended Audience :: Developers
Classifier: License :: OSI Approved :: MIT License
Classifier: Operating System :: OS Independent
Classifier: Programming Language :: Python :: 3.10
Classifier: Programming Language :: Python :: 3.11
Classifier: Programming Language :: Python :: 3.12
Classifier: Topic :: Security :: Cryptography
Classifier: Topic :: Software Development :: Version Control :: Git
Classifier: Topic :: System :: Archiving :: Backup
Classifier: Topic :: Utilities
Requires-Python: >=3.10
License-File: LICENSE
Requires-Dist: cryptography>=3.4.8
Requires-Dist: python-gnupg>=0.5.0
Requires-Dist: pathspec>=0.11.0
Provides-Extra: dev
Requires-Dist: pytest>=7.0.0; extra == "dev"
Requires-Dist: pytest-cov>=4.0.0; extra == "dev"
Requires-Dist: black>=23.0.0; extra == "dev"
Requires-Dist: ruff>=0.1.0; extra == "dev"
Requires-Dist: isort>=5.12.0; extra == "dev"
Requires-Dist: mypy>=1.0.0; extra == "dev"
Provides-Extra: security
Requires-Dist: bandit>=1.7.0; extra == "security"
Requires-Dist: safety>=2.0.0; extra == "security"
Dynamic: home-page
Dynamic: license-file
Dynamic: requires-python
